[1,0,0,[["cc.JsonAsset",["_name","json"],1]],[[0,0,1,3]],[[0,"535",{"scale":0.95,"cups":[{"type":0,"pos":{"x":180,"y":-540},"colorIds":[0,4,108,5]},{"type":0,"pos":{"x":310,"y":300},"colorIds":[3,10,6,2]},{"type":0,"pos":{"x":0,"y":-290},"colorIds":[4,108,2,103]},{"type":0,"pos":{"x":250,"y":-10},"colorIds":[0,10,5,103]},{"type":0,"pos":{"x":180,"y":-280},"colorIds":[9,108,2,107]},{"type":0,"pos":{"x":-180,"y":-280},"colorIds":[0,6,107,1]},{"type":0,"pos":{"x":-250,"y":-10},"colorIds":[0,8,10,4]},{"type":0,"pos":{"x":-310,"y":300},"colorIds":[3,2,5,6]},{"type":0,"pos":{"x":90,"y":-30},"colorIds":[0,4,8,103]},{"type":1,"pos":{"x":300,"y":-340},"colorIds":[0,0,0,0]},{"type":1,"pos":{"x":-300,"y":-340},"colorIds":[0,0,0,0]},{"type":14,"pos":{"x":-180,"y":-540},"colorIds":[3,9,1,8]},{"type":15,"lockType":1,"pos":{"x":0,"y":200},"colorIds":[9,3,9,1]},{"type":3,"frozenUnlockCount":1,"pos":{"x":-150,"y":260},"colorIds":[8,107,3,5]},{"type":12,"maskUnlockColorId":8,"maskUnlockCount":1,"bombTime":120,"pos":{"x":150,"y":260},"colorIds":[1,10,8,1006]},{"type":0,"pos":{"x":-90,"y":-30},"colorIds":[0,0,0,7]}]}]],0,0,[],[],[]]