{"paths":{"0":["倒水春节活动/Calender/bg_date",0],"1":["倒水春节活动/Calender/btn_home",0],"2":["spine/zhuye6",3],"3":["倒水春节活动/Calender/icon_Circular progress",0],"4":["倒水春节活动/img/event_5",0],"5":["倒水春节活动/img/event_1",0],"6":["倒水春节活动/Notify/btn_participate",0],"7":["倒水春节活动/Calender/icon_date_horse",0],"8":["倒水春节活动/Calender/icon_couplet_right",0],"9":["10",0],"10":["icon_coin_big",0],"11":["倒水春节活动/Calender/bg_Task Background",0],"12":["倒水春节活动/Calender/title_Spring Festival",0],"13":["倒水春节活动/img/event_8",0],"14":["倒水春节活动/Calender/bg_date_reward",0],"15":["倒水春节活动/Calender/btn_go",0],"16":["倒水春节活动/img/42",0],"17":["spine/zhuye6",0],"18":["倒水春节活动/Notify/icon_notify_horse",0],"19":["倒水春节活动/icon_horseshoe",0],"20":["倒水春节活动/Calender/bar_attendance record",0],"21":["倒水春节活动/Calender/bar_bg_attendance record",0],"22":["倒水春节活动/Notify/btn_cloes",0],"23":["倒水春节活动/img/event_6",0],"24":["倒水春节活动/Notify/bg_Spring Festival",0],"25":["倒水春节活动/Calender/bar_bg_progress",0],"26":["倒水春节活动/redEnvelopeAni/hbxl",3],"27":["倒水春节活动/Calender/bg_reward",0],"28":["倒水春节活动/img/41",0],"29":["倒水春节活动/Calender/icon_couplet_left",0],"30":["倒水春节活动/img/event_4",0],"31":["倒水春节活动/Calender/icon_sfx",0],"32":["倒水春节活动/Calender/icon_Claimed",0],"33":["倒水春节活动/redEnvelopeAni/hbxl",0],"34":["倒水春节活动/text_Introduction",0],"35":["倒水春节活动/Calender/bar_progress",0],"36":["倒水春节活动/Calender/icon_coin",0],"37":["倒水春节活动/img/event_2",0],"38":["倒水春节活动/img/40",0],"39":["倒水春节活动/Calender/bg_progress",0],"40":["倒水春节活动/Calender/bg_Circular progress",0],"41":["倒水春节活动/Calender/btn_question mark",0],"42":["倒水春节活动/Calender/bg_Spring Festival date",0],"43":["倒水春节活动/img/event_9",0],"44":["倒水春节活动/Calender/bg_Spring Festival_date",0],"45":["倒水春节活动/img/event_7",0],"46":["倒水春节活动/img/event_3",0],"47":["倒水春节活动/Calender/bg_date_claimed",0],"48":["倒水春节活动/img/event_8",1,1],"49":["倒水春节活动/Calender/bar_bg_progress",1,1],"50":["倒水春节活动/img/event_3",1,1],"51":["倒水春节活动/Calender/bar_attendance record",1,1],"52":["倒水春节活动/Calender/title_Spring Festival",1,1],"53":["倒水春节活动/Calender/bg_Task Background",1,1],"54":["倒水春节活动/Calender/btn_home",1,1],"55":["spine/zhuye6.atlas",5],"56":["icon_coin_big",1,1],"57":["倒水春节活动/img/event_6",1,1],"58":["EventRewardPanel",2],"59":["倒水春节活动/Calender/bg_date_reward",1,1],"60":["倒水春节活动/Notify/icon_notify_horse",1,1],"61":["fwPrefab",2],"62":["倒水春节活动/img/42",1,1],"63":["倒水春节活动/img/event_7",1,1],"64":["EventNotifyPanel",2],"65":["倒水春节活动/Calender/icon_couplet_left",1,1],"66":["倒水春节活动/Calender/icon_date_horse",1,1],"67":["倒水春节活动/img/event_2",1,1],"68":["倒水春节活动/Calender/btn_question mark",1,1],"69":["倒水春节活动/Calender/bg_date",1,1],"70":["EventRewardItem",2],"71":["倒水春节活动/img/event_5",1,1],"72":["倒水春节活动/img/40",1,1],"74":["倒水春节活动/Calender/bg_Circular progress",1,1],"75":["倒水春节活动/Calender/icon_coin",1,1],"76":["倒水春节活动/img/event_4",1,1],"77":["倒水春节活动/Calender/icon_Circular progress",1,1],"78":["倒水春节活动/Calender/bg_reward",1,1],"79":["倒水春节活动/img/event_1",1,1],"80":["倒水春节活动/Calender/bar_bg_attendance record",1,1],"81":["倒水春节活动/Calender/btn_go",1,1],"82":["10",1,1],"83":["倒水春节活动/Calender/bar_progress",1,1],"84":["倒水春节活动/redEnvelopeAni/hbxl.atlas",5],"85":["spine/zhuye6",4],"86":["倒水春节活动/Calender/bg_Spring Festival date",1,1],"87":["EventRewardAllPanel",2],"88":["倒水春节活动/redEnvelopeAni/hbxl",4],"89":["倒水春节活动/Calender/icon_Claimed",1,1],"90":["倒水春节活动/Calender/bg_progress",1,1],"91":["倒水春节活动/img/41",1,1],"92":["倒水春节活动/img/event_9",1,1],"93":["倒水春节活动/Notify/btn_cloes",1,1],"94":["倒水春节活动/Calender/icon_sfx",1,1],"95":["倒水春节活动/icon_horseshoe",1,1],"96":["spine/zhuye6",1,1],"97":["倒水春节活动/text_Introduction",1,1],"98":["倒水春节活动/Calender/icon_couplet_right",1,1],"99":["倒水春节活动/Calender/bg_date_claimed",1,1],"100":["EventResignPanel",2],"101":["EventEffectPanel",2],"102":["倒水春节活动/redEnvelopeAni/hbxl",1,1],"103":["倒水春节活动/Calender/bg_Spring Festival_date",1,1],"104":["倒水春节活动/Notify/btn_participate",1,1],"105":["倒水春节活动/Notify/bg_Spring Festival",1,1],"106":["EventPanel",2],"107":["EventDescPanel",2]},"types":["cc.Texture2D","cc.SpriteFrame","cc.Prefab","cc.Asset","sp.SkeletonData","cc.TextAsset"],"uuids":["04TlRvgINH5o5P+z1oDJpL","04g9a49XFGxb8zEsdNBcS3","09yc0X0kRAqIbOdimD/frb","0axZ0r+4dFLYU5dLqbm297","13YJeWoaVNcKkzz8S2yGZ0","14pRrWHR9GuohYaBihqBxr","195+X6/0ROJKzv28nYg2k4","21ndj3aYlLxpg9haLfnIu6","22l1l4j5FLjq5PBioO9H7N","2dI1MZOaNF5ZPGaYSVZlE3","309DsUTydB64YZTB/xbQ1Y","36zQRI9kdGxZvq3+gn4slB","44TlHc52hK4LL7UrwsXBf0","4eSy/DcoBF7IucLDyZx6Bw","5dmoQqQs5MlafLGt09zWjY","5eLrHmtGhKaJ1lPP35pmjW","63SLRSGTpN065VlNwjwh5i","66vEvC7whFcqbnIox3DEfT","76hoO516BE25zN5RIzYRnL","77gN/JG3hCfaknttAdtnIw","829cATKp5NPIYNJcU+lqTh","88M2zPaVJHlpKctA172o66","90whmHirdBjaUuTMzbXzq/","91o/O1CVhEaqnG7ILF+6rx","9cFYBXjlZFwp7+X+in46BF","a4LKEdhW9G5JSeM85ZNQ3i","a6YPYulc1BAaV7/rcfkk8g","a9wWkUiYVMHqgUxb3d09VN","abBmkNfoVG8pw0Rj2G3XEb","abpJMHMZ5PcpiLBkpkNLOP","ae/kTInFFASpeC5IWWiKcN","b1Pi7esDdASqKORKB0A1bz","c5fevC8xtDGJphDg1eers7","c5oMG4URNChZuq3+xUlGbB","c5qa5g4txEApEX3zHSakWF","cd81qkVABH86iU8e1AxwPa","d4ot6stFFKhqx4kvlUk0nO","d5JCsn9SdAm6aO5Jh/Z4EW","d5NNy/XYdAh7Bh2x2t01Mz","d59M/3cpRMuKVuyUvNgdB+","d83jpA5ipFnr94qcBky3H5","daMV7vWrFAJbinam+nUBYT","daV8EO0fRE+rQFXrTnjBQt","e1J5oyBchBE5/MIc0DC6C/","f1Uvm5PZ9HYrG8Ph/z28iZ","f6yK9KqBBJg5r2o+5AyDxp","f7nzC2tr9CWJMyM53LMuDF","fcEinRPVhE2r9l9iqwp+Jm","01+ostsKFG2b4KfvbCwwoV","04SExidZVBuJiyRtWL2BVP","06U++oT2hIiIyIKUW3arsO","0b5/zelL1JVasFNnGp+yfG","0b9q6lB45ACruapWhZAb6V","0fOxlZxQ5BGohfuPX6v/ow","1cludKCJNIu6G/4e5bqcUN","1coi5FDtJLVZL72H3geCLp","1c4n/yRLhL0Ik2i96SzGLz","23U6kUbtZJ2amGZGndDnJ3","2eJFJWRz5ICJUtgRbUAp/6","2e1ohndmpAMpWTsd0ec41Y","32OtjGzIFO+LzdXwRo9EJ0","33xtUt6cpMXaBSeW1Ef751","35AIHM7IBLj7rKAzIra8Nq","37qUwAjLROwpkqppXuwswT","39AFhi+lZG74TiGkYJq0br","398PBkMxFAwZYHtdQJT5B7","3dmVHrP65OhpjNKF5xzwMe","40Mj97ZAxIUoa0lY1uHyAG","4cGBfPZcVKZINtxd/IEYmT","4dJGpCZhhHKZJn6TbOHUMJ","5aADdP71JLS763PDx+1A9N","61psgsy89Ip7flkgdjcxqS","6298upwEFKNqgSdAQlMuxk","71VhFCTINJM6/Ky3oX9nBT","72uwKew4xNSIZ8uCOAFxoj","7actM6NBJMb6QMDr9YLdGz","7adBhJfFlFLrQKW6ni86vQ","7dRKrovs1Iu6FiQL14aM17","80/pUJWYBJQ5s1j0/uERnM","833+dM0JBCxZ3oX7guacau","847Romoo1NsKDZFGb8+hZw","865Qr4vstFiIpFei+eXvFp","88TpVWFyxB46Nuuekm5tmR","8bF/iMn05Mp597+eGTfIfo","8beLOu5r5IZoZJegVWpmfj","8fZF7LKAlK3JdGRowfw4kx","91fIDdASBAe7q5GnVOpVZJ","910A1g0Q1G9ZVp71bdnQVW","92t45vft1ERKLREzsajRsn","9f3/uQuLFHL7YviDo0AAOk","a0qkAOphRFwYDqjgPCb1JP","a3HSAri+tMUoaYy2Y8eYNT","a4K4D+vORNOL3VDFddB58L","b35KOgghlO9ZvYXmUvgHlf","b6YCeqIGVBIr/GpgLLGBYL","ba7vspTGJBkKPailUQUgNH","bdSKv87sVEEZPeiy6D5MUv","c1TmmHDCtN55/8tTOg6Pv4","cbGL1erhZBvL+LPJGOLutn","cboJr7i5BIE6j/X2czNkpw","d61Xglfk9FfInU2/MkjBP+","d7oteFhytLVpL7bar+kSzU","d8nKxhQBVPObkzrjoBm5qV","dcPjxan1ZF2Llmm0xgbf4C","dfeTHT6G5Bv6nWEaNuUdti","e7rbB+tVJEDqkIL3FmwfCF","f34NM+grhNRrHZWQrmQj6y","f5X1pmIoJLEZiL8vdvjiEX","00qThzguBD77S+y0KRPhOM","02delMVqdBD70a/HSD99FK","20AcYRq+BLOpjHmqVlnLGJ","220XlAoMVDQLRJjra9ijjA","27hq1pKjJCkYXIKGrHJmtp","29FYIk+N1GYaeWH/q1NxQO","2bHvxs2F1K4a42zkSExfKw","2c+ip3cXRIDKDeWFhoHalA","2eUsNtWx9PvJuUq39BKIMB","30nV8qdThMG6A4skhduMec","31kXI6k41PE6N1J4EOYSU3","34GavVzP9D1b8vFuS2PnXo","34hoK3XfVPPog7buVbkx5J","37I5q0GcJP+79VvyHSPGQ+","3fmVImi7xG3ZHx5IRJkx0l","47bSGdduZJupJhqnjoQ/4y","47spzTtJ9LVapQH+sSGAQG","4935rTAA9JQ7c4vzr04Nid","54buaybO1CP4tL3mL5qNcs","59VBYt5TlEDpYxBJ4ofoJV","740Hcuk5FGOZ0w/hnbAKBB","75ZbN/EzpMK4gN6RwDBQB5","7a/QZLET9IDreTiBfRn2PD","7dJX/lXIxNOYjFc7vdplYz","7deu9k0a9IaqHI81GcVTPO","88jYS1tR9Iv41fLjUu0nYz","9d7B6IRVJDga113x0/ihTb","a2MjXRFdtLlYQ5ouAFv/+R","a35XKLb9VNnILY4ODsyzyk","a6Eu01gNFANZGtIAgIBxEJ","a7iiRaRYtE96RsvA90swN9","b3XbxtLQdOoociumuMEWGr","bdrI+tqS9K46C3Of8imyXS","c2ALbKM/1ISJnpLej20U/9","c21j+15zdOzqCIJFzg9skp","c6ZafLqmFEVI9MQw5mgZYN","e1z9/7b4tKnLOqEBBBgrtt","e2QHejH9JKvrtBdnLQ3+f+","ecpdLyjvZBwrvm+cedCcQy","eeLPdcUxVCDI39sT8k68P8","efP0nKhlFLTLNbul13/ZYp","f62ftUnHRBd7cyk8UGJ9//","f7mlM4pB9E+7SGZQLqquLG","ffwQKRkcZJIb2E9q0pVuXN"],"scenes":{},"redirect":[108,0,109,1,110,0,111,0,112,0,114,0,115,0,116,2,117,0,118,0,120,0,121,0,122,0,123,0,124,0,125,0,126,0,127,0,128,0,129,0,130,1,131,0,132,0,133,3,136,4,137,0,138,0,139,0,140,0,144,0,145,2,146,1,147,0,148,0,149,0,150,0,151,0],"deps":["Texture","internal","Animation","Font","TextureSideMode"],"packs":{"0385bb805":[0,1,3,4,5,6,7,8,9,10,11,12,13,14,15,16,17,73,18,19,20,21,22,23,24,25,27,28,29,30,31,32,33,34,35,36,37,38,39,40,41,42,43,44,45,46,47],"0838d15f4":[82,101],"0b955ebea":[48,49,50,51,52,53,54,57,59,61,119,62,63,65,67,68,69,71,72,74,76,77,78,79,80,83,86,134,90,91,92,94,95,141,142,143,98,99,103,106],"0d6906dae":[70,87],"0de788c26":[60,64,93,105]},"name":"Event2","importBase":"import","nativeBase":"native","debug":false,"isZip":false,"encrypted":false,"versions":{"import":["0385bb805","e1b08","0838d15f4","c0537",2,"8c4e7","0b955ebea","976fe","0d6906dae","7226a","0de788c26","17888",55,"227a9",56,"be129",113,"6dda3",58,"bf032",66,"a6b8c",75,"57311",81,"f8649",84,"68b8d",85,"423ed",88,"c1b28",89,"4ff8b",135,"43d76",26,"56570",96,"ee806",97,"14765",100,"b6ceb",102,"daf97",104,"ee801",107,"16f49"],"native":[0,"206bf",1,"45c1f",2,"fd9f4",3,"d54b6",4,"ded0c",5,"16eb8",6,"53081",7,"d70ce",8,"74a4d",9,"35018",10,"3b003",11,"fb945",12,"427ba",13,"2c7ff",14,"4d6da",15,"78318",16,"f4f68",17,"11f1c",73,"c06a9",18,"2fdb9",19,"ee3b9",20,"34852",21,"7d0ae",22,"eb883",23,"3c662",24,"114df",25,"b2da9",26,"0c48e",27,"56c5b",28,"8fe08",29,"0ed36",30,"a5f77",31,"d649f",32,"3eb36",33,"b4a88",34,"8388c",35,"f1fb4",36,"16b42",37,"e5d30",38,"5c33a",39,"a9316",40,"3c7f9",41,"b40ca",42,"bec6d",43,"2b0d2",44,"f0847",45,"614e7",46,"045bf",47,"c5a01"]}}